marshmallow_cbor/__init__.py
marshmallow_cbor/fields.py
marshmallow_cbor/schema.py
marshmallow_cbor-0.1.1.dist-info/LICENSE
marshmallow_cbor-0.1.1.dist-info/METADATA
marshmallow_cbor-0.1.1.dist-info/WHEEL
marshmallow_cbor-0.1.1.dist-info/top_level.txt
marshmallow_cbor-0.1.1.dist-info/RECORD
