Metadata-Version: 2.1
Name: marshmallow-cbor
Version: 0.1.1
Summary: Marshmallow support for CBOR encoding
Home-page: UNKNOWN
Author: Kio Smallwood
Author-email: kio@mothers-arms.co.uk
License: MIT
Project-URL: Source Code, https://github.com/Sekenre/marshmallow_cbor
Project-URL: Issue Tracker, https://github.com/Sekenre/marshmallow_cbor/issues
Keywords: marshmallow,serialization,rest,cbor,api,marshal,marshalling,deserialization,validation,schema
Platform: UNKNOWN
Classifier: Development Status :: 3 - Alpha
Classifier: Intended Audience :: Developers
Classifier: License :: OSI Approved :: MIT License
Classifier: Programming Language :: Python
Classifier: Programming Language :: Python :: 3
Classifier: Programming Language :: Python :: 3.6
Classifier: Programming Language :: Python :: 3.7
Classifier: Programming Language :: Python :: 3.8
Classifier: Programming Language :: Python :: 3.9
Requires-Python: >=3.6
License-File: LICENSE
Requires-Dist: marshmallow (>=3.8)
Requires-Dist: cbor2 (>=5.4)
Provides-Extra: doc
Requires-Dist: sphinx-rtd-theme ; extra == 'doc'
Requires-Dist: sphinx-autodoc-typehints (>=1.2.0) ; extra == 'doc'
Provides-Extra: test
Requires-Dist: pytest ; extra == 'test'
Requires-Dist: pytest-cov ; extra == 'test'
